gamedig-0.8.0.dist-info/METADATA
gamedig-0.8.0.dist-info/WHEEL
gamedig-0.8.0.dist-info/licenses/LICENSE
gamedig/__init__.py
gamedig/__init__.pyi
gamedig/gamedig.cpython-39-arm-linux-gnueabihf.so
gamedig/py.typed
gamedig-0.8.0.dist-info/RECORD
