Metadata-Version: 2.4
Name: gamedig
Version: 0.8.0
Classifier: Development Status :: 5 - Production/Stable
Classifier: Intended Audience :: Developers
Classifier: License :: OSI Approved :: MIT License
Classifier: Operating System :: OS Independent
Classifier: Programming Language :: Rust
Classifier: Programming Language :: Python
Classifier: Programming Language :: Python :: 3
Classifier: Programming Language :: Python :: 3.9
Classifier: Programming Language :: Python :: 3.10
Classifier: Programming Language :: Python :: 3.11
Classifier: Programming Language :: Python :: 3.12
Classifier: Programming Language :: Python :: 3.13
Classifier: Programming Language :: Python :: 3.14
Classifier: Programming Language :: Python :: Implementation :: CPython
Classifier: Programming Language :: Python :: Implementation :: PyPy
Classifier: Topic :: Software Development :: Libraries
Classifier: Topic :: Software Development :: Libraries :: Python Modules
License-File: LICENSE
Summary: Unofficial high-level Python bindings for the Rust gamedig crate
Author-email: Jonathan Ehwald <github@ehwald.info>
License-Expression: MIT
Requires-Python: >=3.9
Project-URL: homepage, https://github.com/DoctorJohn/python-gamedig
Project-URL: repository, https://github.com/DoctorJohn/python-gamedig
Project-URL: documentation, https://github.com/DoctorJohn/python-gamedig
